foytr_awe/__init__.py
foytr_awe/app.py
foytr_awe-0.1.0.dist-info/METADATA
foytr_awe-0.1.0.dist-info/WHEEL
foytr_awe-0.1.0.dist-info/top_level.txt
foytr_awe-0.1.0.dist-info/RECORD
